primer_x402/__init__.py
primer_x402/cli.py
primer_x402/errors.py
primer_x402/payee.py
primer_x402/payer.py
primer_x402/signer.py
primer_x402/utils.py
primer_x402/wallet.py
primer_x402/testing/__init__.py
primer_x402/testing/fixtures.py
primer_x402/testing/mock_facilitator.py
primer_x402/testing/test_payment.py
primer_x402-0.5.0.dist-info/METADATA
primer_x402-0.5.0.dist-info/WHEEL
primer_x402-0.5.0.dist-info/entry_points.txt
primer_x402-0.5.0.dist-info/top_level.txt
primer_x402-0.5.0.dist-info/RECORD
