Metadata-Version: 2.4
Name: primer-x402
Version: 0.5.0
Summary: Python SDK for x402 payments - pay and charge for APIs with stablecoins. OpenClaw compatible.
Author-email: Primer Systems <support@primer.systems>
License: MIT
Project-URL: Homepage, https://x402.org
Project-URL: Documentation, https://x402.org/docs
Project-URL: Repository, https://github.com/Primer-Systems/x402
Project-URL: Issues, https://github.com/Primer-Systems/x402/issues
Keywords: x402,payments,crypto,usdc,stablecoin,ethereum,base,eip-3009,web3,ai-payments,micropayments,http-402,ai-agents,openclaw,moltbot,clawdbot
Classifier: Development Status :: 4 - Beta
Classifier: Intended Audience :: Developers
Classifier: License :: OSI Approved :: MIT License
Classifier: Operating System :: OS Independent
Classifier: Programming Language :: Python :: 3
Classifier: Programming Language :: Python :: 3.9
Classifier: Programming Language :: Python :: 3.10
Classifier: Programming Language :: Python :: 3.11
Classifier: Programming Language :: Python :: 3.12
Classifier: Topic :: Software Development :: Libraries :: Python Modules
Classifier: Topic :: Internet :: WWW/HTTP
Classifier: Topic :: Office/Business :: Financial
Requires-Python: >=3.9
Requires-Dist: web3>=6.0.0
Requires-Dist: eth-account>=0.11.0
Requires-Dist: requests>=2.28.0
Provides-Extra: httpx
Requires-Dist: httpx>=0.24.0; extra == "httpx"
Provides-Extra: flask
Requires-Dist: flask>=2.0.0; extra == "flask"
Provides-Extra: fastapi
Requires-Dist: fastapi>=0.100.0; extra == "fastapi"
Requires-Dist: starlette>=0.27.0; extra == "fastapi"
Provides-Extra: all
Requires-Dist: httpx>=0.24.0; extra == "all"
Requires-Dist: flask>=2.0.0; extra == "all"
Requires-Dist: fastapi>=0.100.0; extra == "all"
Requires-Dist: starlette>=0.27.0; extra == "all"
Provides-Extra: dev
Requires-Dist: pytest>=7.0.0; extra == "dev"
Requires-Dist: pytest-cov>=4.0.0; extra == "dev"
Requires-Dist: httpx>=0.24.0; extra == "dev"
Requires-Dist: flask>=2.0.0; extra == "dev"
Requires-Dist: fastapi>=0.100.0; extra == "dev"
Requires-Dist: starlette>=0.27.0; extra == "dev"
